{
  "schemaVersion": "cellfence.baseline.v1",
  "generatedAt": "2026-07-12T15:09:48.738Z",
  "cells": {
    "schema": {
      "ownedPathPatterns": 1,
      "publicSymbols": 22,
      "publicSurfaceLines": 367,
      "crossCellDependencies": 0,
      "resourceAccesses": []
    },
    "engine": {
      "ownedPathPatterns": 1,
      "publicSymbols": 36,
      "publicSurfaceLines": 2607,
      "crossCellDependencies": 1,
      "resourceAccesses": []
    },
    "cli": {
      "ownedPathPatterns": 1,
      "publicSymbols": 1,
      "publicSurfaceLines": 492,
      "crossCellDependencies": 1,
      "resourceAccesses": []
    },
    "github-action": {
      "ownedPathPatterns": 1,
      "publicSymbols": 1,
      "publicSurfaceLines": 32,
      "crossCellDependencies": 1,
      "resourceAccesses": []
    },
    "trace": {
      "ownedPathPatterns": 1,
      "publicSymbols": 6,
      "publicSurfaceLines": 163,
      "crossCellDependencies": 1,
      "resourceAccesses": []
    }
  }
}
